agentbox/__init__.py
agentbox/api/__init__.py
agentbox/api/client/__init__.py
agentbox/api/client/api/__init__.py
agentbox/api/client/api/sandboxes/__init__.py
agentbox/api/client/api/sandboxes/delete_sandboxes_sandbox_id.py
agentbox/api/client/api/sandboxes/get_sandboxes.py
agentbox/api/client/api/sandboxes/get_sandboxes_metrics.py
agentbox/api/client/api/sandboxes/get_sandboxes_sandbox_id.py
agentbox/api/client/api/sandboxes/get_sandboxes_sandbox_id_adb.py
agentbox/api/client/api/sandboxes/get_sandboxes_sandbox_id_adb_public_info.py
agentbox/api/client/api/sandboxes/get_sandboxes_sandbox_id_instance_auth_info.py
agentbox/api/client/api/sandboxes/get_sandboxes_sandbox_id_instance_no.py
agentbox/api/client/api/sandboxes/get_sandboxes_sandbox_id_logs.py
agentbox/api/client/api/sandboxes/get_sandboxes_sandbox_id_metrics.py
agentbox/api/client/api/sandboxes/get_sandboxes_sandbox_id_ssh.py
agentbox/api/client/api/sandboxes/get_v2_sandboxes.py
agentbox/api/client/api/sandboxes/post_sandboxes.py
agentbox/api/client/api/sandboxes/post_sandboxes_sandbox_id_connect.py
agentbox/api/client/api/sandboxes/post_sandboxes_sandbox_id_model_information.py
agentbox/api/client/api/sandboxes/post_sandboxes_sandbox_id_pause.py
agentbox/api/client/api/sandboxes/post_sandboxes_sandbox_id_refreshes.py
agentbox/api/client/api/sandboxes/post_sandboxes_sandbox_id_resume.py
agentbox/api/client/api/sandboxes/post_sandboxes_sandbox_id_timeout.py
agentbox/api/client/client.py
agentbox/api/client/errors.py
agentbox/api/client/models/__init__.py
agentbox/api/client/models/access_token_response.py
agentbox/api/client/models/access_token_response_user.py
agentbox/api/client/models/access_token_response_weak_password.py
agentbox/api/client/models/agent_box_template_build.py
agentbox/api/client/models/agent_box_template_build_status.py
agentbox/api/client/models/alert_context.py
agentbox/api/client/models/alert_context_common_annotations.py
agentbox/api/client/models/alert_context_common_labels.py
agentbox_python_sdk-1.0.9.dist-info/METADATA
agentbox_python_sdk-1.0.9.dist-info/WHEEL
agentbox_python_sdk-1.0.9.dist-info/RECORD
