Metadata-Version: 2.3
Name: agentbox-python-sdk
Version: 1.0.9
Summary: AgentBox Python SDK that give agents cloud environments
License: MIT
Author: agentbox
Author-email: agentbox@mail.agentbox.cloud
Requires-Python: >=3.9,<4.0
Classifier: License :: OSI Approved :: MIT License
Classifier: Programming Language :: Python :: 3
Classifier: Programming Language :: Python :: 3.9
Classifier: Programming Language :: Python :: 3.10
Classifier: Programming Language :: Python :: 3.11
Classifier: Programming Language :: Python :: 3.12
Classifier: Programming Language :: Python :: 3.13
Requires-Dist: adb_shell (>=0.4.4)
Requires-Dist: aiofiles (>=0.4.0)
Requires-Dist: async-timeout (>=3.0.0)
Requires-Dist: attrs (>=23.2.0)
Requires-Dist: httpcore (>=1.0.5,<2.0.0)
Requires-Dist: httpx (>=0.27.0,<1.0.0)
Requires-Dist: packaging (>=24.1)
Requires-Dist: paramiko (>=3.5.1,<4.0.0)
Requires-Dist: protobuf (>=5.29.4,<6.0.0)
Requires-Dist: python-dateutil (>=2.8.2)
Requires-Dist: typing-extensions (>=4.1.0)
Project-URL: Bug Tracker, https://github.com/agentbox-cloud/issues
Project-URL: Homepage, https://agentbox.cloud/
Project-URL: Repository, https://github.com/agentbox-cloud/agentbox
